pyxfs/__init__.py
pyxfs/core/__init__.py
pyxfs/core/path.py
pyxfs/s3/__init__.py
pyxfs/s3/path.py
pyxfs-0.1.0.dist-info/licenses/LICENSE
pyxfs-0.1.0.dist-info/METADATA
pyxfs-0.1.0.dist-info/WHEEL
pyxfs-0.1.0.dist-info/top_level.txt
pyxfs-0.1.0.dist-info/RECORD
