Metadata-Version: 2.4
Name: pyxfs
Version: 0.1.0
Summary: Universal filesystem interface with pluggable backends (local, S3, SFTP, ...).
Author-email: Nicolas FILLOT <nfillot.pro@gmail.com>
License: MIT
Project-URL: Homepage, https://github.com/Platob/pyXFS
Project-URL: Repository, https://github.com/Platob/pyXFS
Project-URL: Issues, https://github.com/Platob/pyXFS/issues
Keywords: filesystem,storage,s3,sftp,io,abstraction
Classifier: Development Status :: 3 - Alpha
Classifier: Intended Audience :: Developers
Classifier: License :: OSI Approved :: MIT License
Classifier: Programming Language :: Python :: 3
Classifier: Programming Language :: Python :: 3 :: Only
Classifier: Programming Language :: Python :: 3.8
Classifier: Programming Language :: Python :: 3.9
Classifier: Programming Language :: Python :: 3.10
Classifier: Programming Language :: Python :: 3.11
Classifier: Programming Language :: Python :: 3.12
Classifier: Topic :: System :: Filesystems
Requires-Python: >=3.8
License-File: LICENSE
Provides-Extra: s3
Requires-Dist: boto3>=1.20; extra == "s3"
Provides-Extra: sftp
Requires-Dist: paramiko>=2.10; extra == "sftp"
Dynamic: license-file
